[
  {
    "symbol": "ZYDUSLIFE",
    "name": "Zydus Lifesciences Ltd",
    "side": "BUY",
    "suggested_on": "2026-05-19",
    "suggested_close": 1018.9,
    "entry": 1024.15,
    "fill_trigger": 1036.4398,
    "stoploss": 979.5738,
    "strict_stoploss": 1018.8,
    "swing_low": 835.5,
    "swing_high": 1018.8,
    "targets": [
      {
        "name": "T1",
        "ratio": 0.5,
        "price": 927.15
      },
      {
        "name": "T2",
        "ratio": 0.618,
        "price": 948.7794
      },
      {
        "name": "T3",
        "ratio": 1.5,
        "price": 1110.4499999999998
      },
      {
        "name": "T4",
        "ratio": 1.618,
        "price": 1132.0794
      },
      {
        "name": "T5",
        "ratio": 2.618,
        "price": 1315.3793999999998
      }
    ],
    "status": "open",
    "fill_date": "2026-05-20",
    "fill_price": 1036.4398,
    "exit_date": null,
    "exit_price": null,
    "exit_reason": null,
    "days_held": null,
    "pnl_pct": null,
    "last_checked": "2026-05-27"
  },
  {
    "symbol": "IGL",
    "name": "Indraprastha Gas Ltd",
    "side": "BUY",
    "suggested_on": "2026-05-19",
    "suggested_close": 157.35,
    "entry": 155.968,
    "fill_trigger": 157.83961599999998,
    "stoploss": null,
    "strict_stoploss": 141.74,
    "swing_low": 141.74,
    "swing_high": 229.0,
    "targets": [
      {
        "name": "T1",
        "ratio": 0.5,
        "price": 185.37
      },
      {
        "name": "T2",
        "ratio": 0.618,
        "price": 195.66667999999999
      },
      {
        "name": "T3",
        "ratio": 1.5,
        "price": 272.63
      },
      {
        "name": "T4",
        "ratio": 1.618,
        "price": 282.92668000000003
      },
      {
        "name": "T5",
        "ratio": 2.618,
        "price": 370.18667999999997
      }
    ],
    "status": "open",
    "fill_date": "2026-05-20",
    "fill_price": 157.83961599999998,
    "exit_date": null,
    "exit_price": null,
    "exit_reason": null,
    "days_held": null,
    "pnl_pct": null,
    "last_checked": "2026-05-27"
  },
  {
    "symbol": "ECLERX",
    "name": "eClerx Services Ltd",
    "side": "BUY",
    "suggested_on": "2026-05-19",
    "suggested_close": 1553.8,
    "entry": 1560.1799999999998,
    "fill_trigger": 1578.9021599999999,
    "stoploss": null,
    "strict_stoploss": 1375.0,
    "swing_low": 1375.0,
    "swing_high": 4995.0,
    "targets": [
      {
        "name": "T1",
        "ratio": 0.5,
        "price": 3185.0
      },
      {
        "name": "T2",
        "ratio": 0.618,
        "price": 3612.16
      },
      {
        "name": "T3",
        "ratio": 1.5,
        "price": 6805.0
      },
      {
        "name": "T4",
        "ratio": 1.618,
        "price": 7232.160000000001
      },
      {
        "name": "T5",
        "ratio": 2.618,
        "price": 10852.16
      }
    ],
    "status": "open",
    "fill_date": "2026-05-22",
    "fill_price": 1578.9021599999999,
    "exit_date": null,
    "exit_price": null,
    "exit_reason": null,
    "days_held": null,
    "pnl_pct": null,
    "last_checked": "2026-05-27"
  },
  {
    "symbol": "GPIL",
    "name": "Godawari Power & Ispat Ltd",
    "side": "BUY",
    "suggested_on": "2026-05-20",
    "suggested_close": 305.85,
    "entry": 307.175,
    "fill_trigger": 310.8611,
    "stoploss": 266.99199999999996,
    "strict_stoploss": 277.012,
    "swing_low": 145.75,
    "swing_high": 312.75,
    "targets": [
      {
        "name": "T1",
        "ratio": 0.5,
        "price": 229.25
      },
      {
        "name": "T2",
        "ratio": 0.618,
        "price": 248.95600000000002
      },
      {
        "name": "T3",
        "ratio": 1.5,
        "price": 396.25
      },
      {
        "name": "T4",
        "ratio": 1.618,
        "price": 415.956
      },
      {
        "name": "T5",
        "ratio": 2.618,
        "price": 582.9559999999999
      }
    ],
    "status": "pending",
    "fill_date": null,
    "fill_price": null,
    "exit_date": null,
    "exit_price": null,
    "exit_reason": null,
    "days_held": null,
    "pnl_pct": null,
    "last_checked": "2026-05-27"
  },
  {
    "symbol": "MANKIND",
    "name": "Mankind Pharma Ltd",
    "side": "BUY",
    "suggested_on": "2026-05-20",
    "suggested_close": 2583.9,
    "entry": 2568.75,
    "fill_trigger": 2599.575,
    "stoploss": 2401.1072,
    "strict_stoploss": 2534.9,
    "swing_low": 1909.7,
    "swing_high": 2534.9,
    "targets": [
      {
        "name": "T1",
        "ratio": 0.5,
        "price": 2222.3
      },
      {
        "name": "T2",
        "ratio": 0.618,
        "price": 2296.0736
      },
      {
        "name": "T3",
        "ratio": 1.5,
        "price": 2847.5
      },
      {
        "name": "T4",
        "ratio": 1.618,
        "price": 2921.2736000000004
      },
      {
        "name": "T5",
        "ratio": 2.618,
        "price": 3546.4736000000003
      }
    ],
    "status": "open",
    "fill_date": "2026-05-21",
    "fill_price": 2599.575,
    "exit_date": null,
    "exit_price": null,
    "exit_reason": null,
    "days_held": null,
    "pnl_pct": null,
    "last_checked": "2026-05-27"
  },
  {
    "symbol": "MOTHERSON",
    "name": "Samvardhana Motherson International Ltd",
    "side": "BUY",
    "suggested_on": "2026-05-20",
    "suggested_close": 132.17,
    "entry": 133.0795,
    "fill_trigger": 134.676454,
    "stoploss": 123.4227,
    "strict_stoploss": 126.2097,
    "swing_low": 89.7,
    "swing_high": 136.15,
    "targets": [
      {
        "name": "T1",
        "ratio": 0.5,
        "price": 112.92500000000001
      },
      {
        "name": "T2",
        "ratio": 0.618,
        "price": 118.40610000000001
      },
      {
        "name": "T3",
        "ratio": 1.5,
        "price": 159.375
      },
      {
        "name": "T4",
        "ratio": 1.618,
        "price": 164.85610000000003
      },
      {
        "name": "T5",
        "ratio": 2.618,
        "price": 211.30610000000001
      }
    ],
    "status": "open",
    "fill_date": "2026-05-21",
    "fill_price": 134.676454,
    "exit_date": null,
    "exit_price": null,
    "exit_reason": null,
    "days_held": null,
    "pnl_pct": null,
    "last_checked": "2026-05-27"
  },
  {
    "symbol": "ENRIN",
    "name": "Siemens Energy India Ltd",
    "side": "BUY",
    "suggested_on": "2026-05-20",
    "suggested_close": 3459.6,
    "entry": 3334.655,
    "fill_trigger": 3374.67086,
    "stoploss": 3024.678,
    "strict_stoploss": 3099.858,
    "swing_low": 2115.0,
    "swing_high": 3368.0,
    "targets": [
      {
        "name": "T1",
        "ratio": 0.5,
        "price": 2741.5
      },
      {
        "name": "T2",
        "ratio": 0.618,
        "price": 2889.3540000000003
      },
      {
        "name": "T3",
        "ratio": 1.5,
        "price": 3994.5
      },
      {
        "name": "T4",
        "ratio": 1.618,
        "price": 4142.354
      },
      {
        "name": "T5",
        "ratio": 2.618,
        "price": 5395.353999999999
      }
    ],
    "status": "open",
    "fill_date": "2026-05-21",
    "fill_price": 3374.67086,
    "exit_date": null,
    "exit_price": null,
    "exit_reason": null,
    "days_held": null,
    "pnl_pct": null,
    "last_checked": "2026-05-27"
  },
  {
    "symbol": "TATACOMM",
    "name": "Tata Communications Ltd",
    "side": "BUY",
    "suggested_on": "2026-05-20",
    "suggested_close": 1775.6,
    "entry": 1726.3400000000001,
    "fill_trigger": 1747.05608,
    "stoploss": 1582.833,
    "strict_stoploss": 1663.25,
    "swing_low": 1322.5,
    "swing_high": 2004.0,
    "targets": [
      {
        "name": "T1",
        "ratio": 0.5,
        "price": 1663.25
      },
      {
        "name": "T2",
        "ratio": 0.618,
        "price": 1743.667
      },
      {
        "name": "T3",
        "ratio": 1.5,
        "price": 2344.75
      },
      {
        "name": "T4",
        "ratio": 1.618,
        "price": 2425.1670000000004
      },
      {
        "name": "T5",
        "ratio": 2.618,
        "price": 3106.667
      }
    ],
    "status": "open",
    "fill_date": "2026-05-21",
    "fill_price": 1747.05608,
    "exit_date": null,
    "exit_price": null,
    "exit_reason": null,
    "days_held": null,
    "pnl_pct": null,
    "last_checked": "2026-05-27"
  },
  {
    "symbol": "GVT&D",
    "name": "GE Vernova T&D India Ltd",
    "side": "BUY",
    "suggested_on": "2026-05-20",
    "suggested_close": 4679.4,
    "entry": 4626.38,
    "fill_trigger": 4681.89656,
    "stoploss": 4211.730799999999,
    "strict_stoploss": 4351.2788,
    "swing_low": 2523.2,
    "swing_high": 4849.0,
    "targets": [
      {
        "name": "T1",
        "ratio": 0.5,
        "price": 3686.1
      },
      {
        "name": "T2",
        "ratio": 0.618,
        "price": 3960.5443999999998
      },
      {
        "name": "T3",
        "ratio": 1.5,
        "price": 6011.9
      },
      {
        "name": "T4",
        "ratio": 1.618,
        "price": 6286.3444
      },
      {
        "name": "T5",
        "ratio": 2.618,
        "price": 8612.144400000001
      }
    ],
    "status": "open",
    "fill_date": "2026-05-21",
    "fill_price": 4681.89656,
    "exit_date": null,
    "exit_price": null,
    "exit_reason": null,
    "days_held": null,
    "pnl_pct": null,
    "last_checked": "2026-05-27"
  },
  {
    "symbol": "ERIS",
    "name": "ERIS Lifesciences Ltd",
    "side": "BUY",
    "suggested_on": "2026-05-20",
    "suggested_close": 1458.2,
    "entry": 1425.295,
    "fill_trigger": 1442.3985400000001,
    "stoploss": 1200.0,
    "strict_stoploss": 1367.56,
    "swing_low": 1200.0,
    "swing_high": 1910.0,
    "targets": [
      {
        "name": "T1",
        "ratio": 0.5,
        "price": 1555.0
      },
      {
        "name": "T2",
        "ratio": 0.618,
        "price": 1638.78
      },
      {
        "name": "T3",
        "ratio": 1.5,
        "price": 2265.0
      },
      {
        "name": "T4",
        "ratio": 1.618,
        "price": 2348.7799999999997
      },
      {
        "name": "T5",
        "ratio": 2.618,
        "price": 3058.7799999999997
      }
    ],
    "status": "open",
    "fill_date": "2026-05-21",
    "fill_price": 1442.3985400000001,
    "exit_date": null,
    "exit_price": null,
    "exit_reason": null,
    "days_held": null,
    "pnl_pct": null,
    "last_checked": "2026-05-27"
  },
  {
    "symbol": "TIMKEN",
    "name": "Timken India Ltd",
    "side": "BUY",
    "suggested_on": "2026-05-20",
    "suggested_close": 3656.2,
    "entry": 3633.825,
    "fill_trigger": 3677.4309,
    "stoploss": 3438.7266,
    "strict_stoploss": 3491.4726,
    "swing_low": 2800.5,
    "swing_high": 3679.6,
    "targets": [
      {
        "name": "T1",
        "ratio": 0.5,
        "price": 3240.05
      },
      {
        "name": "T2",
        "ratio": 0.618,
        "price": 3343.7838
      },
      {
        "name": "T3",
        "ratio": 1.5,
        "price": 4119.15
      },
      {
        "name": "T4",
        "ratio": 1.618,
        "price": 4222.8838
      },
      {
        "name": "T5",
        "ratio": 2.618,
        "price": 5101.9838
      }
    ],
    "status": "open",
    "fill_date": "2026-05-21",
    "fill_price": 3677.4309,
    "exit_date": null,
    "exit_price": null,
    "exit_reason": null,
    "days_held": null,
    "pnl_pct": null,
    "last_checked": "2026-05-27"
  },
  {
    "symbol": "IRB",
    "name": "IRB Infrastructure Developers Ltd",
    "side": "BUY",
    "suggested_on": "2026-05-21",
    "suggested_close": 22.84,
    "entry": 22.681,
    "fill_trigger": 22.953172000000002,
    "stoploss": null,
    "strict_stoploss": 19.72,
    "swing_low": 19.72,
    "swing_high": 78.15,
    "targets": [
      {
        "name": "T1",
        "ratio": 0.5,
        "price": 48.935
      },
      {
        "name": "T2",
        "ratio": 0.618,
        "price": 55.82974
      },
      {
        "name": "T3",
        "ratio": 1.5,
        "price": 107.36500000000001
      },
      {
        "name": "T4",
        "ratio": 1.618,
        "price": 114.25974000000002
      },
      {
        "name": "T5",
        "ratio": 2.618,
        "price": 172.68974
      }
    ],
    "status": "pending",
    "fill_date": null,
    "fill_price": null,
    "exit_date": null,
    "exit_price": null,
    "exit_reason": null,
    "days_held": null,
    "pnl_pct": null,
    "last_checked": "2026-05-27"
  },
  {
    "symbol": "GRASIM",
    "name": "Grasim Industries Ltd",
    "side": "BUY",
    "suggested_on": "2026-05-21",
    "suggested_close": 3154.5,
    "entry": 3108.45,
    "fill_trigger": 3145.7513999999996,
    "stoploss": 2899.2728,
    "strict_stoploss": 3007.3,
    "swing_low": 2502.5,
    "swing_high": 3007.3,
    "targets": [
      {
        "name": "T1",
        "ratio": 0.5,
        "price": 2754.9
      },
      {
        "name": "T2",
        "ratio": 0.618,
        "price": 2814.4664000000002
      },
      {
        "name": "T3",
        "ratio": 1.5,
        "price": 3259.7000000000003
      },
      {
        "name": "T4",
        "ratio": 1.618,
        "price": 3319.2664000000004
      },
      {
        "name": "T5",
        "ratio": 2.618,
        "price": 3824.0664000000006
      }
    ],
    "status": "open",
    "fill_date": "2026-05-22",
    "fill_price": 3145.7513999999996,
    "exit_date": null,
    "exit_price": null,
    "exit_reason": null,
    "days_held": null,
    "pnl_pct": null,
    "last_checked": "2026-05-27"
  },
  {
    "symbol": "SAMMAANCAP",
    "name": "Sammaan Capital Ltd",
    "side": "BUY",
    "suggested_on": "2026-05-21",
    "suggested_close": 154.26,
    "entry": 153.82999999999998,
    "fill_trigger": 155.67595999999998,
    "stoploss": 144.0922,
    "strict_stoploss": 153.4289,
    "swing_low": 129.0,
    "swing_high": 192.95,
    "targets": [
      {
        "name": "T1",
        "ratio": 0.5,
        "price": 160.975
      },
      {
        "name": "T2",
        "ratio": 0.618,
        "price": 168.5211
      },
      {
        "name": "T3",
        "ratio": 1.5,
        "price": 224.92499999999998
      },
      {
        "name": "T4",
        "ratio": 1.618,
        "price": 232.47109999999998
      },
      {
        "name": "T5",
        "ratio": 2.618,
        "price": 296.42109999999997
      }
    ],
    "status": "closed",
    "fill_date": "2026-05-22",
    "fill_price": 155.67595999999998,
    "exit_date": "2026-05-25",
    "exit_price": 168.5211,
    "exit_reason": "target_t2",
    "days_held": 3,
    "pnl_pct": 8.251203332871704,
    "last_checked": "2026-05-25"
  },
  {
    "symbol": "JSWCEMENT",
    "name": "JSW Cement Ltd",
    "side": "BUY",
    "suggested_on": "2026-05-21",
    "suggested_close": 127.46,
    "entry": 127.2475,
    "fill_trigger": 128.77447,
    "stoploss": null,
    "strict_stoploss": null,
    "swing_low": null,
    "swing_high": 137.83,
    "targets": [],
    "status": "open",
    "fill_date": "2026-05-22",
    "fill_price": 128.77447,
    "exit_date": null,
    "exit_price": null,
    "exit_reason": null,
    "days_held": null,
    "pnl_pct": null,
    "last_checked": "2026-05-27"
  },
  {
    "symbol": "IGIL",
    "name": "International Gemmological Institute (India) Ltd",
    "side": "BUY",
    "suggested_on": "2026-05-21",
    "suggested_close": 375.25,
    "entry": 369.725,
    "fill_trigger": 374.16170000000005,
    "stoploss": 358.1117,
    "strict_stoploss": 363.9887,
    "swing_low": 287.0,
    "swing_high": 384.95,
    "targets": [
      {
        "name": "T1",
        "ratio": 0.5,
        "price": 335.975
      },
      {
        "name": "T2",
        "ratio": 0.618,
        "price": 347.5331
      },
      {
        "name": "T3",
        "ratio": 1.5,
        "price": 433.92499999999995
      },
      {
        "name": "T4",
        "ratio": 1.618,
        "price": 445.4831
      },
      {
        "name": "T5",
        "ratio": 2.618,
        "price": 543.4331
      }
    ],
    "status": "open",
    "fill_date": "2026-05-22",
    "fill_price": 374.16170000000005,
    "exit_date": null,
    "exit_price": null,
    "exit_reason": null,
    "days_held": null,
    "pnl_pct": null,
    "last_checked": "2026-05-27"
  },
  {
    "symbol": "RHIM",
    "name": "RHI Magnesita India Ltd",
    "side": "BUY",
    "suggested_on": "2026-05-21",
    "suggested_close": 398.8,
    "entry": 406.3975,
    "fill_trigger": 411.27427,
    "stoploss": null,
    "strict_stoploss": 323.05,
    "swing_low": 323.05,
    "swing_high": 824.0,
    "targets": [
      {
        "name": "T1",
        "ratio": 0.5,
        "price": 573.525
      },
      {
        "name": "T2",
        "ratio": 0.618,
        "price": 632.6370999999999
      },
      {
        "name": "T3",
        "ratio": 1.5,
        "price": 1074.475
      },
      {
        "name": "T4",
        "ratio": 1.618,
        "price": 1133.5871
      },
      {
        "name": "T5",
        "ratio": 2.618,
        "price": 1634.5370999999998
      }
    ],
    "status": "open",
    "fill_date": "2026-05-26",
    "fill_price": 411.27427,
    "exit_date": null,
    "exit_price": null,
    "exit_reason": null,
    "days_held": null,
    "pnl_pct": null,
    "last_checked": "2026-05-27"
  },
  {
    "symbol": "TECHNOE",
    "name": "Techno Electric & Engineering Company Ltd",
    "side": "BUY",
    "suggested_on": "2026-05-21",
    "suggested_close": 1294.3,
    "entry": 1258.375,
    "fill_trigger": 1273.4755,
    "stoploss": 1208.0256,
    "strict_stoploss": 1235.9615999999999,
    "swing_low": 870.0,
    "swing_high": 1335.6,
    "targets": [
      {
        "name": "T1",
        "ratio": 0.5,
        "price": 1102.8
      },
      {
        "name": "T2",
        "ratio": 0.618,
        "price": 1157.7408
      },
      {
        "name": "T3",
        "ratio": 1.5,
        "price": 1568.3999999999999
      },
      {
        "name": "T4",
        "ratio": 1.618,
        "price": 1623.3408
      },
      {
        "name": "T5",
        "ratio": 2.618,
        "price": 2088.9407999999994
      }
    ],
    "status": "closed",
    "fill_date": "2026-05-22",
    "fill_price": 1273.4755,
    "exit_date": "2026-05-26",
    "exit_price": 1208.0256,
    "exit_reason": "stoploss",
    "days_held": 4,
    "pnl_pct": -5.13947068475209,
    "last_checked": "2026-05-26"
  },
  {
    "symbol": "APOLLOHOSP",
    "name": "Apollo Hospitals Enterprise Ltd",
    "side": "BUY",
    "suggested_on": "2026-05-21",
    "suggested_close": 8308.5,
    "entry": 8236.575,
    "fill_trigger": 8335.413900000001,
    "stoploss": 7862.531,
    "strict_stoploss": 8180.0,
    "swing_low": 6696.5,
    "swing_high": 8180.0,
    "targets": [
      {
        "name": "T1",
        "ratio": 0.5,
        "price": 7438.25
      },
      {
        "name": "T2",
        "ratio": 0.618,
        "price": 7613.303
      },
      {
        "name": "T3",
        "ratio": 1.5,
        "price": 8921.75
      },
      {
        "name": "T4",
        "ratio": 1.618,
        "price": 9096.803
      },
      {
        "name": "T5",
        "ratio": 2.618,
        "price": 10580.303
      }
    ],
    "status": "open",
    "fill_date": "2026-05-22",
    "fill_price": 8335.413900000001,
    "exit_date": null,
    "exit_price": null,
    "exit_reason": null,
    "days_held": null,
    "pnl_pct": null,
    "last_checked": "2026-05-27"
  },
  {
    "symbol": "WHIRLPOOL",
    "name": "Whirlpool of India Ltd",
    "side": "BUY",
    "suggested_on": "2026-05-21",
    "suggested_close": 877.45,
    "entry": 865.425,
    "fill_trigger": 875.8100999999999,
    "stoploss": 821.3016,
    "strict_stoploss": 861.1742,
    "swing_low": 756.85,
    "swing_high": 1029.95,
    "targets": [
      {
        "name": "T1",
        "ratio": 0.5,
        "price": 893.4000000000001
      },
      {
        "name": "T2",
        "ratio": 0.618,
        "price": 925.6258
      },
      {
        "name": "T3",
        "ratio": 1.5,
        "price": 1166.5
      },
      {
        "name": "T4",
        "ratio": 1.618,
        "price": 1198.7258000000002
      },
      {
        "name": "T5",
        "ratio": 2.618,
        "price": 1471.8258
      }
    ],
    "status": "pending",
    "fill_date": null,
    "fill_price": null,
    "exit_date": null,
    "exit_price": null,
    "exit_reason": null,
    "days_held": null,
    "pnl_pct": null,
    "last_checked": "2026-05-27"
  },
  {
    "symbol": "PAGEIND",
    "name": "Page Industries Ltd",
    "side": "BUY",
    "suggested_on": "2026-05-21",
    "suggested_close": 38380.0,
    "entry": 38711.25,
    "fill_trigger": 39175.785,
    "stoploss": 36371.67,
    "strict_stoploss": 36914.37,
    "swing_low": 29805.0,
    "swing_high": 38850.0,
    "targets": [
      {
        "name": "T1",
        "ratio": 0.5,
        "price": 34327.5
      },
      {
        "name": "T2",
        "ratio": 0.618,
        "price": 35394.81
      },
      {
        "name": "T3",
        "ratio": 1.5,
        "price": 43372.5
      },
      {
        "name": "T4",
        "ratio": 1.618,
        "price": 44439.81
      },
      {
        "name": "T5",
        "ratio": 2.618,
        "price": 53484.81
      }
    ],
    "status": "open",
    "fill_date": "2026-05-22",
    "fill_price": 39175.785,
    "exit_date": null,
    "exit_price": null,
    "exit_reason": null,
    "days_held": null,
    "pnl_pct": null,
    "last_checked": "2026-05-27"
  },
  {
    "symbol": "NAUKRI",
    "name": "Info Edge (India) Ltd",
    "side": "BUY",
    "suggested_on": "2026-05-22",
    "suggested_close": 960.95,
    "entry": 955.7950000000001,
    "fill_trigger": 967.2645400000001,
    "stoploss": null,
    "strict_stoploss": 914.8,
    "swing_low": 914.8,
    "swing_high": 9128.9,
    "targets": [
      {
        "name": "T1",
        "ratio": 0.5,
        "price": 5021.85
      },
      {
        "name": "T2",
        "ratio": 0.618,
        "price": 5991.1138
      },
      {
        "name": "T3",
        "ratio": 1.5,
        "price": 13235.95
      },
      {
        "name": "T4",
        "ratio": 1.618,
        "price": 14205.213800000001
      },
      {
        "name": "T5",
        "ratio": 2.618,
        "price": 22419.3138
      }
    ],
    "status": "open",
    "fill_date": "2026-05-25",
    "fill_price": 967.2645400000001,
    "exit_date": null,
    "exit_price": null,
    "exit_reason": null,
    "days_held": null,
    "pnl_pct": null,
    "last_checked": "2026-05-27"
  },
  {
    "symbol": "HONASA",
    "name": "Honasa Consumer Ltd",
    "side": "BUY",
    "suggested_on": "2026-05-22",
    "suggested_close": 384.35,
    "entry": 392.1125,
    "fill_trigger": 396.81785,
    "stoploss": 339.8118,
    "strict_stoploss": 364.7,
    "swing_low": 248.4,
    "swing_high": 364.7,
    "targets": [
      {
        "name": "T1",
        "ratio": 0.5,
        "price": 306.55
      },
      {
        "name": "T2",
        "ratio": 0.618,
        "price": 320.2734
      },
      {
        "name": "T3",
        "ratio": 1.5,
        "price": 422.85
      },
      {
        "name": "T4",
        "ratio": 1.618,
        "price": 436.5734
      },
      {
        "name": "T5",
        "ratio": 2.618,
        "price": 552.8734
      }
    ],
    "status": "open",
    "fill_date": "2026-05-26",
    "fill_price": 396.81785,
    "exit_date": null,
    "exit_price": null,
    "exit_reason": null,
    "days_held": null,
    "pnl_pct": null,
    "last_checked": "2026-05-27"
  },
  {
    "symbol": "NYKAA",
    "name": "FSN E-Commerce Ventures Ltd",
    "side": "BUY",
    "suggested_on": "2026-05-22",
    "suggested_close": 277.25,
    "entry": 278.15250000000003,
    "fill_trigger": 281.49033000000003,
    "stoploss": 249.78820000000002,
    "strict_stoploss": 257.6302,
    "swing_low": 154.9,
    "swing_high": 285.6,
    "targets": [
      {
        "name": "T1",
        "ratio": 0.5,
        "price": 220.25
      },
      {
        "name": "T2",
        "ratio": 0.618,
        "price": 235.67260000000002
      },
      {
        "name": "T3",
        "ratio": 1.5,
        "price": 350.95000000000005
      },
      {
        "name": "T4",
        "ratio": 1.618,
        "price": 366.37260000000003
      },
      {
        "name": "T5",
        "ratio": 2.618,
        "price": 497.0726000000001
      }
    ],
    "status": "pending",
    "fill_date": null,
    "fill_price": null,
    "exit_date": null,
    "exit_price": null,
    "exit_reason": null,
    "days_held": null,
    "pnl_pct": null,
    "last_checked": "2026-05-27"
  },
  {
    "symbol": "LICI",
    "name": "Life Insurance Corporation of India",
    "side": "BUY",
    "suggested_on": "2026-05-22",
    "suggested_close": 812.95,
    "entry": 825.7925,
    "fill_trigger": 835.70201,
    "stoploss": 782.506,
    "strict_stoploss": 820.247,
    "swing_low": 721.5,
    "swing_high": 980.0,
    "targets": [
      {
        "name": "T1",
        "ratio": 0.5,
        "price": 850.75
      },
      {
        "name": "T2",
        "ratio": 0.618,
        "price": 881.2529999999999
      },
      {
        "name": "T3",
        "ratio": 1.5,
        "price": 1109.25
      },
      {
        "name": "T4",
        "ratio": 1.618,
        "price": 1139.7530000000002
      },
      {
        "name": "T5",
        "ratio": 2.618,
        "price": 1398.253
      }
    ],
    "status": "closed",
    "fill_date": "2026-05-25",
    "fill_price": 835.70201,
    "exit_date": "2026-05-26",
    "exit_price": 850.75,
    "exit_reason": "target_t1",
    "days_held": 1,
    "pnl_pct": 1.8006406374444506,
    "last_checked": "2026-05-26"
  },
  {
    "symbol": "MINDACORP",
    "name": "Minda Corporation Ltd",
    "side": "BUY",
    "suggested_on": "2026-05-22",
    "suggested_close": 574.65,
    "entry": 563.9225,
    "fill_trigger": 570.68957,
    "stoploss": 544.225,
    "strict_stoploss": 562.0961,
    "swing_low": 468.5,
    "swing_high": 619.95,
    "targets": [
      {
        "name": "T1",
        "ratio": 0.5,
        "price": 544.225
      },
      {
        "name": "T2",
        "ratio": 0.618,
        "price": 562.0961
      },
      {
        "name": "T3",
        "ratio": 1.5,
        "price": 695.6750000000001
      },
      {
        "name": "T4",
        "ratio": 1.618,
        "price": 713.5461
      },
      {
        "name": "T5",
        "ratio": 2.618,
        "price": 864.9961000000001
      }
    ],
    "status": "open",
    "fill_date": "2026-05-25",
    "fill_price": 570.68957,
    "exit_date": null,
    "exit_price": null,
    "exit_reason": null,
    "days_held": null,
    "pnl_pct": null,
    "last_checked": "2026-05-27"
  },
  {
    "symbol": "GAIL",
    "name": "GAIL (India) Ltd",
    "side": "BUY",
    "suggested_on": "2026-05-25",
    "suggested_close": 168.67,
    "entry": 167.1,
    "fill_trigger": 169.1052,
    "stoploss": 150.50948,
    "strict_stoploss": 160.50026,
    "swing_low": 134.36,
    "swing_high": 202.79,
    "targets": [
      {
        "name": "T1",
        "ratio": 0.5,
        "price": 168.575
      },
      {
        "name": "T2",
        "ratio": 0.618,
        "price": 176.64974
      },
      {
        "name": "T3",
        "ratio": 1.5,
        "price": 237.005
      },
      {
        "name": "T4",
        "ratio": 1.618,
        "price": 245.07974
      },
      {
        "name": "T5",
        "ratio": 2.618,
        "price": 313.50973999999997
      }
    ],
    "status": "closed",
    "fill_date": "2026-05-26",
    "fill_price": 169.1052,
    "exit_date": "2026-05-27",
    "exit_price": 168.575,
    "exit_reason": "target_t1",
    "days_held": 1,
    "pnl_pct": -0.31353264121979363,
    "last_checked": "2026-05-27"
  },
  {
    "symbol": "NH",
    "name": "Narayana Hrudayalaya Ltd",
    "side": "BUY",
    "suggested_on": "2026-05-25",
    "suggested_close": 1940.0,
    "entry": 1935.645,
    "fill_trigger": 1958.87274,
    "stoploss": 1773.3632,
    "strict_stoploss": 1887.4184,
    "swing_low": 1589.0,
    "swing_high": 2370.2,
    "targets": [
      {
        "name": "T1",
        "ratio": 0.5,
        "price": 1979.6
      },
      {
        "name": "T2",
        "ratio": 0.618,
        "price": 2071.7816
      },
      {
        "name": "T3",
        "ratio": 1.5,
        "price": 2760.7999999999997
      },
      {
        "name": "T4",
        "ratio": 1.618,
        "price": 2852.9816
      },
      {
        "name": "T5",
        "ratio": 2.618,
        "price": 3634.1815999999994
      }
    ],
    "status": "pending",
    "fill_date": null,
    "fill_price": null,
    "exit_date": null,
    "exit_price": null,
    "exit_reason": null,
    "days_held": null,
    "pnl_pct": null,
    "last_checked": "2026-05-27"
  },
  {
    "symbol": "EICHERMOT",
    "name": "Eicher Motors Ltd",
    "side": "BUY",
    "suggested_on": "2026-05-25",
    "suggested_close": 7414.0,
    "entry": 7334.35,
    "fill_trigger": 7422.3622000000005,
    "stoploss": 6863.968,
    "strict_stoploss": 7125.016,
    "swing_low": 6442.0,
    "swing_high": 8230.0,
    "targets": [
      {
        "name": "T1",
        "ratio": 0.5,
        "price": 7336.0
      },
      {
        "name": "T2",
        "ratio": 0.618,
        "price": 7546.984
      },
      {
        "name": "T3",
        "ratio": 1.5,
        "price": 9124.0
      },
      {
        "name": "T4",
        "ratio": 1.618,
        "price": 9334.984
      },
      {
        "name": "T5",
        "ratio": 2.618,
        "price": 11122.984
      }
    ],
    "status": "closed",
    "fill_date": "2026-05-26",
    "fill_price": 7422.3622000000005,
    "exit_date": "2026-05-27",
    "exit_price": 7336.0,
    "exit_reason": "target_t1",
    "days_held": 1,
    "pnl_pct": -1.1635406313100782,
    "last_checked": "2026-05-27"
  },
  {
    "symbol": "TORNTPHARM",
    "name": "Torrent Pharmaceuticals Ltd",
    "side": "BUY",
    "suggested_on": "2026-05-25",
    "suggested_close": 4572.6,
    "entry": 4621.595,
    "fill_trigger": 4677.05414,
    "stoploss": 4198.008900000001,
    "strict_stoploss": 4555.1,
    "swing_low": 2886.45,
    "swing_high": 4555.1,
    "targets": [
      {
        "name": "T1",
        "ratio": 0.5,
        "price": 3720.775
      },
      {
        "name": "T2",
        "ratio": 0.618,
        "price": 3917.6757000000002
      },
      {
        "name": "T3",
        "ratio": 1.5,
        "price": 5389.425000000001
      },
      {
        "name": "T4",
        "ratio": 1.618,
        "price": 5586.325700000001
      },
      {
        "name": "T5",
        "ratio": 2.618,
        "price": 7254.975700000001
      }
    ],
    "status": "pending",
    "fill_date": null,
    "fill_price": null,
    "exit_date": null,
    "exit_price": null,
    "exit_reason": null,
    "days_held": null,
    "pnl_pct": null,
    "last_checked": "2026-05-27"
  },
  {
    "symbol": "POWERINDIA",
    "name": "Hitachi Energy India Ltd",
    "side": "BUY",
    "suggested_on": "2026-05-26",
    "suggested_close": 35995.0,
    "entry": 35374.5,
    "fill_trigger": 35798.994,
    "stoploss": 31094.913999999997,
    "strict_stoploss": 32333.254,
    "swing_low": 16111.0,
    "swing_high": 36750.0,
    "targets": [
      {
        "name": "T1",
        "ratio": 0.5,
        "price": 26430.5
      },
      {
        "name": "T2",
        "ratio": 0.618,
        "price": 28865.902000000002
      },
      {
        "name": "T3",
        "ratio": 1.5,
        "price": 47069.5
      },
      {
        "name": "T4",
        "ratio": 1.618,
        "price": 49504.902
      },
      {
        "name": "T5",
        "ratio": 2.618,
        "price": 70143.902
      }
    ],
    "status": "open",
    "fill_date": "2026-05-27",
    "fill_price": 35798.994,
    "exit_date": null,
    "exit_price": null,
    "exit_reason": null,
    "days_held": null,
    "pnl_pct": null,
    "last_checked": "2026-05-27"
  },
  {
    "symbol": "JPPOWER",
    "name": "Jaiprakash Power Ventures Ltd",
    "side": "BUY",
    "suggested_on": "2026-05-27",
    "suggested_close": 22.87,
    "entry": 21.2535,
    "fill_trigger": 21.508542,
    "stoploss": 19.3594,
    "strict_stoploss": 21.05,
    "swing_low": 13.15,
    "swing_high": 21.05,
    "targets": [
      {
        "name": "T1",
        "ratio": 0.5,
        "price": 17.1
      },
      {
        "name": "T2",
        "ratio": 0.618,
        "price": 18.0322
      },
      {
        "name": "T3",
        "ratio": 1.5,
        "price": 25.0
      },
      {
        "name": "T4",
        "ratio": 1.618,
        "price": 25.9322
      },
      {
        "name": "T5",
        "ratio": 2.618,
        "price": 33.8322
      }
    ],
    "status": "pending",
    "fill_date": null,
    "fill_price": null,
    "exit_date": null,
    "exit_price": null,
    "exit_reason": null,
    "days_held": null,
    "pnl_pct": null,
    "last_checked": "2026-05-27"
  },
  {
    "symbol": "COALINDIA",
    "name": "Coal India Ltd",
    "side": "BUY",
    "suggested_on": "2026-05-27",
    "suggested_close": 463.05,
    "entry": 450.345,
    "fill_trigger": 455.74914,
    "stoploss": 420.25,
    "strict_stoploss": 437.006,
    "swing_low": 349.25,
    "swing_high": 491.25,
    "targets": [
      {
        "name": "T1",
        "ratio": 0.5,
        "price": 420.25
      },
      {
        "name": "T2",
        "ratio": 0.618,
        "price": 437.006
      },
      {
        "name": "T3",
        "ratio": 1.5,
        "price": 562.25
      },
      {
        "name": "T4",
        "ratio": 1.618,
        "price": 579.0060000000001
      },
      {
        "name": "T5",
        "ratio": 2.618,
        "price": 721.006
      }
    ],
    "status": "pending",
    "fill_date": null,
    "fill_price": null,
    "exit_date": null,
    "exit_price": null,
    "exit_reason": null,
    "days_held": null,
    "pnl_pct": null,
    "last_checked": "2026-05-27"
  },
  {
    "symbol": "ATGL",
    "name": "Adani Total Gas Ltd",
    "side": "BUY",
    "suggested_on": "2026-05-27",
    "suggested_close": 808.55,
    "entry": 777.8225,
    "fill_trigger": 787.15637,
    "stoploss": 637.3706,
    "strict_stoploss": 684.9,
    "swing_low": 462.8,
    "swing_high": 684.9,
    "targets": [
      {
        "name": "T1",
        "ratio": 0.5,
        "price": 573.85
      },
      {
        "name": "T2",
        "ratio": 0.618,
        "price": 600.0578
      },
      {
        "name": "T3",
        "ratio": 1.5,
        "price": 795.95
      },
      {
        "name": "T4",
        "ratio": 1.618,
        "price": 822.1578
      },
      {
        "name": "T5",
        "ratio": 2.618,
        "price": 1044.2577999999999
      }
    ],
    "status": "pending",
    "fill_date": null,
    "fill_price": null,
    "exit_date": null,
    "exit_price": null,
    "exit_reason": null,
    "days_held": null,
    "pnl_pct": null,
    "last_checked": "2026-05-27"
  },
  {
    "symbol": "AIAENG",
    "name": "AIA Engineering Ltd",
    "side": "BUY",
    "suggested_on": "2026-05-27",
    "suggested_close": 4428.1,
    "entry": 4327.24,
    "fill_trigger": 4379.16688,
    "stoploss": 3948.2300000000005,
    "strict_stoploss": 4206.1,
    "swing_low": 3001.1,
    "swing_high": 4206.1,
    "targets": [
      {
        "name": "T1",
        "ratio": 0.5,
        "price": 3603.6000000000004
      },
      {
        "name": "T2",
        "ratio": 0.618,
        "price": 3745.79
      },
      {
        "name": "T3",
        "ratio": 1.5,
        "price": 4808.6
      },
      {
        "name": "T4",
        "ratio": 1.618,
        "price": 4950.790000000001
      },
      {
        "name": "T5",
        "ratio": 2.618,
        "price": 6155.790000000001
      }
    ],
    "status": "pending",
    "fill_date": null,
    "fill_price": null,
    "exit_date": null,
    "exit_price": null,
    "exit_reason": null,
    "days_held": null,
    "pnl_pct": null,
    "last_checked": "2026-05-27"
  },
  {
    "symbol": "JKTYRE",
    "name": "JK Tyre & Industries Ltd",
    "side": "BUY",
    "suggested_on": "2026-05-27",
    "suggested_close": 413.3,
    "entry": 417.07,
    "fill_trigger": 422.07484,
    "stoploss": null,
    "strict_stoploss": 357.7,
    "swing_low": 357.7,
    "swing_high": 611.9,
    "targets": [
      {
        "name": "T1",
        "ratio": 0.5,
        "price": 484.79999999999995
      },
      {
        "name": "T2",
        "ratio": 0.618,
        "price": 514.7955999999999
      },
      {
        "name": "T3",
        "ratio": 1.5,
        "price": 739.0
      },
      {
        "name": "T4",
        "ratio": 1.618,
        "price": 768.9956
      },
      {
        "name": "T5",
        "ratio": 2.618,
        "price": 1023.1956
      }
    ],
    "status": "pending",
    "fill_date": null,
    "fill_price": null,
    "exit_date": null,
    "exit_price": null,
    "exit_reason": null,
    "days_held": null,
    "pnl_pct": null,
    "last_checked": "2026-05-27"
  },
  {
    "symbol": "ZEEL",
    "name": "Zee Entertainment Enterprises Ltd",
    "side": "BUY",
    "suggested_on": "2026-05-27",
    "suggested_close": 91.46,
    "entry": 88.5755,
    "fill_trigger": 89.638406,
    "stoploss": 68.0,
    "strict_stoploss": 87.75319999999999,
    "swing_low": 68.0,
    "swing_high": 151.7,
    "targets": [
      {
        "name": "T1",
        "ratio": 0.5,
        "price": 109.85
      },
      {
        "name": "T2",
        "ratio": 0.618,
        "price": 119.72659999999999
      },
      {
        "name": "T3",
        "ratio": 1.5,
        "price": 193.54999999999998
      },
      {
        "name": "T4",
        "ratio": 1.618,
        "price": 203.42659999999998
      },
      {
        "name": "T5",
        "ratio": 2.618,
        "price": 287.12659999999994
      }
    ],
    "status": "pending",
    "fill_date": null,
    "fill_price": null,
    "exit_date": null,
    "exit_price": null,
    "exit_reason": null,
    "days_held": null,
    "pnl_pct": null,
    "last_checked": "2026-05-27"
  },
  {
    "symbol": "PINELABS",
    "name": "Pine Labs Ltd",
    "side": "BUY",
    "suggested_on": "2026-05-27",
    "suggested_close": 145.83,
    "entry": 141.649,
    "fill_trigger": 143.348788,
    "stoploss": null,
    "strict_stoploss": null,
    "swing_low": 143.34,
    "swing_high": null,
    "targets": [],
    "status": "pending",
    "fill_date": null,
    "fill_price": null,
    "exit_date": null,
    "exit_price": null,
    "exit_reason": null,
    "days_held": null,
    "pnl_pct": null,
    "last_checked": "2026-05-27"
  },
  {
    "symbol": "EXIDEIND",
    "name": "Exide Industries Ltd",
    "side": "BUY",
    "suggested_on": "2026-05-27",
    "suggested_close": 394.15,
    "entry": 382.4375,
    "fill_trigger": 387.02675,
    "stoploss": 359.0,
    "strict_stoploss": 375.992,
    "swing_low": 287.0,
    "swing_high": 431.0,
    "targets": [
      {
        "name": "T1",
        "ratio": 0.5,
        "price": 359.0
      },
      {
        "name": "T2",
        "ratio": 0.618,
        "price": 375.992
      },
      {
        "name": "T3",
        "ratio": 1.5,
        "price": 503.0
      },
      {
        "name": "T4",
        "ratio": 1.618,
        "price": 519.992
      },
      {
        "name": "T5",
        "ratio": 2.618,
        "price": 663.992
      }
    ],
    "status": "pending",
    "fill_date": null,
    "fill_price": null,
    "exit_date": null,
    "exit_price": null,
    "exit_reason": null,
    "days_held": null,
    "pnl_pct": null,
    "last_checked": "2026-05-27"
  },
  {
    "symbol": "GRANULES",
    "name": "Granules India Ltd",
    "side": "BUY",
    "suggested_on": "2026-05-27",
    "suggested_close": 782.6,
    "entry": 779.6825,
    "fill_trigger": 789.03869,
    "stoploss": 698.0432000000001,
    "strict_stoploss": 773.2,
    "swing_low": 422.0,
    "swing_high": 773.2,
    "targets": [
      {
        "name": "T1",
        "ratio": 0.5,
        "price": 597.6
      },
      {
        "name": "T2",
        "ratio": 0.618,
        "price": 639.0416
      },
      {
        "name": "T3",
        "ratio": 1.5,
        "price": 948.8000000000001
      },
      {
        "name": "T4",
        "ratio": 1.618,
        "price": 990.2416000000001
      },
      {
        "name": "T5",
        "ratio": 2.618,
        "price": 1341.4416
      }
    ],
    "status": "pending",
    "fill_date": null,
    "fill_price": null,
    "exit_date": null,
    "exit_price": null,
    "exit_reason": null,
    "days_held": null,
    "pnl_pct": null,
    "last_checked": "2026-05-27"
  },
  {
    "symbol": "CUMMINSIND",
    "name": "Cummins India Ltd",
    "side": "BUY",
    "suggested_on": "2026-05-27",
    "suggested_close": 6027.5,
    "entry": 5785.575,
    "fill_trigger": 5855.0019,
    "stoploss": 4851.933,
    "strict_stoploss": 5470.5,
    "swing_low": 2580.0,
    "swing_high": 5470.5,
    "targets": [
      {
        "name": "T1",
        "ratio": 0.5,
        "price": 4025.25
      },
      {
        "name": "T2",
        "ratio": 0.618,
        "price": 4366.329
      },
      {
        "name": "T3",
        "ratio": 1.5,
        "price": 6915.75
      },
      {
        "name": "T4",
        "ratio": 1.618,
        "price": 7256.829000000001
      },
      {
        "name": "T5",
        "ratio": 2.618,
        "price": 10147.329
      }
    ],
    "status": "pending",
    "fill_date": null,
    "fill_price": null,
    "exit_date": null,
    "exit_price": null,
    "exit_reason": null,
    "days_held": null,
    "pnl_pct": null,
    "last_checked": "2026-05-27"
  },
  {
    "symbol": "GILLETTE",
    "name": "Gillette India Ltd",
    "side": "BUY",
    "suggested_on": "2026-05-27",
    "suggested_close": 8273.5,
    "entry": 8199.95,
    "fill_trigger": 8298.349400000001,
    "stoploss": null,
    "strict_stoploss": 7206.0,
    "swing_low": 7206.0,
    "swing_high": 11500.0,
    "targets": [
      {
        "name": "T1",
        "ratio": 0.5,
        "price": 9353.0
      },
      {
        "name": "T2",
        "ratio": 0.618,
        "price": 9859.692
      },
      {
        "name": "T3",
        "ratio": 1.5,
        "price": 13647.0
      },
      {
        "name": "T4",
        "ratio": 1.618,
        "price": 14153.692
      },
      {
        "name": "T5",
        "ratio": 2.618,
        "price": 18447.692
      }
    ],
    "status": "pending",
    "fill_date": null,
    "fill_price": null,
    "exit_date": null,
    "exit_price": null,
    "exit_reason": null,
    "days_held": null,
    "pnl_pct": null,
    "last_checked": "2026-05-27"
  }
]